crawler/__init__.py
crawler/crawler.py
pyjstage/__init__.py
pyjstage/entry.py
pyjstage/errors.py
pyjstage/order.py
pyjstage/parser.py
pyjstage/pyjstage.py
pyjstage/result.py
pyjstage/service.py
pyjstage/status.py
pyjstage-0.0.2.dist-info/LICENSE
pyjstage-0.0.2.dist-info/METADATA
pyjstage-0.0.2.dist-info/WHEEL
pyjstage-0.0.2.dist-info/top_level.txt
pyjstage-0.0.2.dist-info/RECORD
